entry/__init__.py
entry/main.py
entry/args/__init__.py
entry/args/create.py
entry/args/platform.py
entry/args/template.gitignore
entry/args/templete.gitignore
emong_egret_framework-1.0.3.1.dist-info/METADATA
emong_egret_framework-1.0.3.1.dist-info/WHEEL
emong_egret_framework-1.0.3.1.dist-info/entry_points.txt
emong_egret_framework-1.0.3.1.dist-info/top_level.txt
emong_egret_framework-1.0.3.1.dist-info/RECORD
