Metadata-Version: 2.1
Name: emong-egret-framework
Version: 1.0.3.1
Summary: egret framework for emong
Home-page: UNKNOWN
Author: qkrsogusl3
Author-email: qkrsogusl3@gmail.com
License: UNKNOWN
Platform: UNKNOWN
Classifier: Programming Language :: Python :: 3
Classifier: License :: OSI Approved :: MIT License
Classifier: Operating System :: OS Independent
Requires-Python: >=3
Requires-Dist: GitPython
Requires-Dist: pycryptodome
Requires-Dist: paramiko
Requires-Dist: cryptography (==2.4.2)
